sustaincity_iagent/__init__.py
sustaincity_iagent/config.py
sustaincity_iagent/predict.py
sustaincity_iagent/train.py
sustaincity_iagent/IAgents/__init__.py
sustaincity_iagent/IAgents/CHN/Scenario_I.zip
sustaincity_iagent/IAgents/CHN/Scenario_II.zip
sustaincity_iagent/IAgents/CHN/Scenario_III.zip
sustaincity_iagent/IAgents/CHN/Scenario_IV.zip
sustaincity_iagent/IAgents/CHN/Scenario_IX.zip
sustaincity_iagent/IAgents/CHN/Scenario_V.zip
sustaincity_iagent/IAgents/CHN/Scenario_VI.zip
sustaincity_iagent/IAgents/CHN/Scenario_VII.zip
sustaincity_iagent/IAgents/CHN/Scenario_VIII.zip
sustaincity_iagent/IAgents/CHN/__init__.py
sustaincity_iagent/IAgents/EU/Scenario_I.zip
sustaincity_iagent/IAgents/EU/Scenario_II.zip
sustaincity_iagent/IAgents/EU/Scenario_III.zip
sustaincity_iagent/IAgents/EU/Scenario_IV.zip
sustaincity_iagent/IAgents/EU/Scenario_IX.zip
sustaincity_iagent/IAgents/EU/Scenario_V.zip
sustaincity_iagent/IAgents/EU/Scenario_VI.zip
sustaincity_iagent/IAgents/EU/Scenario_VII.zip
sustaincity_iagent/IAgents/EU/Scenario_VIII.zip
sustaincity_iagent/IAgents/EU/__init__.py
sustaincity_iagent/IAgents/IND/Scenario_I.zip
sustaincity_iagent/IAgents/IND/Scenario_II.zip
sustaincity_iagent/IAgents/IND/Scenario_III.zip
sustaincity_iagent/IAgents/IND/Scenario_IV.zip
sustaincity_iagent/IAgents/IND/Scenario_IX.zip
sustaincity_iagent/IAgents/IND/Scenario_V.zip
sustaincity_iagent/IAgents/IND/Scenario_VI.zip
sustaincity_iagent/IAgents/IND/Scenario_VII.zip
sustaincity_iagent/IAgents/IND/Scenario_VIII.zip
sustaincity_iagent/IAgents/IND/__init__.py
sustaincity_iagent/IAgents/JPN/Scenario_I.zip
sustaincity_iagent/IAgents/JPN/Scenario_II.zip
sustaincity_iagent/IAgents/JPN/Scenario_III.zip
sustaincity_iagent/IAgents/JPN/Scenario_IV.zip
sustaincity_iagent/IAgents/JPN/Scenario_IX.zip
sustaincity_iagent/IAgents/JPN/Scenario_V.zip
sustaincity_iagent/IAgents/JPN/Scenario_VI.zip
sustaincity_iagent/IAgents/JPN/Scenario_VII.zip
sustaincity_iagent/IAgents/JPN/Scenario_VIII.zip
sustaincity_iagent-1.0.0.dist-info/licenses/LICENSE
sustaincity_iagent-1.0.0.dist-info/METADATA
sustaincity_iagent-1.0.0.dist-info/WHEEL
sustaincity_iagent-1.0.0.dist-info/top_level.txt
sustaincity_iagent-1.0.0.dist-info/RECORD
