Metadata-Version: 2.4
Name: sustaincity-iagent
Version: 1.0.0
Summary: SustainCity Intelligent-Agent Framework for municipal solid waste (MSW) management.
Author-email: Qilin Cao <caoql23@mails.jlu.edu.cn>
License: Apache-2.0
Project-URL: Homepage, https://github.com/Kirin-Ciao/SustainCity-IAgent-Framework
Project-URL: Repository, https://github.com/Kirin-Ciao/SustainCity-IAgent-Framework
Project-URL: Issue Tracker, https://github.com/Kirin-Ciao/SustainCity-IAgent-Framework/issues
Project-URL: Zenodo, https://doi.org/10.5281/zenodo.17853494
Keywords: reinforcement-learning,RL,MSW,municipal solid waste,waste management,sustainability,intelligent agents
Classifier: Development Status :: 3 - Alpha
Classifier: Intended Audience :: Science/Research
Classifier: License :: OSI Approved :: Apache Software License
Classifier: Programming Language :: Python :: 3
Classifier: Programming Language :: Python :: 3.11
Classifier: Topic :: Scientific/Engineering
Classifier: Topic :: Scientific/Engineering :: Information Analysis
Classifier: Environment :: Other Environment
Requires-Python: >=3.10
License-File: LICENSE
Requires-Dist: numpy>=1.23
Requires-Dist: pandas>=1.5
Requires-Dist: stable-baselines3>=2.0.0
Requires-Dist: gymnasium>=0.29
Requires-Dist: matplotlib>=3.6
Requires-Dist: openpyxl>=3.1
Dynamic: license-file
